odoo8_addon_l10n_pe_toponyms-8.0.1.0.0-py2.7-nspkg.pth
odoo_addons/l10n_pe_toponyms/__openerp__.py
odoo_addons/l10n_pe_toponyms/__init__.py
odoo_addons/l10n_pe_toponyms/README.rst
odoo_addons/l10n_pe_toponyms/security/l10n_pe_security.xml
odoo_addons/l10n_pe_toponyms/security/ir.model.access.csv
odoo_addons/l10n_pe_toponyms/view/country_data.xml
odoo_addons/l10n_pe_toponyms/view/res_country_view.xml
odoo_addons/l10n_pe_toponyms/view/res_company_view.xml
odoo_addons/l10n_pe_toponyms/i18n/es.po
odoo_addons/l10n_pe_toponyms/i18n/es_PE.po
odoo_addons/l10n_pe_toponyms/model/res_partner.py
odoo_addons/l10n_pe_toponyms/model/__init__.py
odoo_addons/l10n_pe_toponyms/model/res_company.py
odoo_addons/l10n_pe_toponyms/data/res_country_data.xml
odoo8_addon_l10n_pe_toponyms-8.0.1.0.0.dist-info/top_level.txt
odoo8_addon_l10n_pe_toponyms-8.0.1.0.0.dist-info/WHEEL
odoo8_addon_l10n_pe_toponyms-8.0.1.0.0.dist-info/RECORD
odoo8_addon_l10n_pe_toponyms-8.0.1.0.0.dist-info/metadata.json
odoo8_addon_l10n_pe_toponyms-8.0.1.0.0.dist-info/DESCRIPTION.rst
odoo8_addon_l10n_pe_toponyms-8.0.1.0.0.dist-info/METADATA
odoo8_addon_l10n_pe_toponyms-8.0.1.0.0.dist-info/namespace_packages.txt
